{
    "swagger": "2.0",
    "info": {
        "description": "这是chatbox api swagger文档.",
        "title": "ChatBox API",
        "contact": {},
        "license": {
            "name": "Apache 2.0",
            "url": "http://www.apache.org/licenses/LICENSE-2.0.html"
        },
        "version": "0.01"
    },
    "host": "localhost:4321",
    "basePath": "/api/v1",
    "paths": {
        "/signup": {
            "post": {
                "description": "使用邮箱密码注册",
                "consumes": [
                    "application/json"
                ],
                "produces": [
                    "application/json"
                ],
                "tags": [
                    "Auth"
                ],
                "summary": "用户注册",
                "responses": {
                    "200": {
                        "description": "OK"
                    }
                }
            }
        }
    },
    "securityDefinitions": {
        "BasicAuth": {
            "type": "basic"
        }
    },
    "externalDocs": {
        "description": "OpenAPI",
        "url": "https://swagger.io/resources/open-api/"
    }
}